splinter/__init__.py
splinter/browser.py
splinter/config.py
splinter/cookie_manager.py
splinter/element_list.py
splinter/exceptions.py
splinter/meta.py
splinter/retry.py
splinter/version.py
splinter/driver/__init__.py
splinter/driver/djangoclient.py
splinter/driver/element_present.py
splinter/driver/find_links.py
splinter/driver/flaskclient.py
splinter/driver/lxmldriver.py
splinter/driver/xpath_utils.py
splinter/driver/zopetestbrowser.py
splinter/driver/webdriver/__init__.py
splinter/driver/webdriver/chrome.py
splinter/driver/webdriver/cookie_manager.py
splinter/driver/webdriver/edge.py
splinter/driver/webdriver/firefox.py
splinter/driver/webdriver/remote.py
splinter/driver/webdriver/remote_connection.py
splinter/driver/webdriver/setup.py
splinter/request_handler/__init__.py
splinter/request_handler/status_code.py
splinter-0.21.0.dist-info/AUTHORS
splinter-0.21.0.dist-info/LICENSE
splinter-0.21.0.dist-info/METADATA
splinter-0.21.0.dist-info/WHEEL
splinter-0.21.0.dist-info/top_level.txt
splinter-0.21.0.dist-info/RECORD
