Metadata-Version: 2.1
Name: splinter
Version: 0.21.0
Summary: browser abstraction for web acceptance testing
Home-page: https://github.com/cobrateam/splinter
Author: CobraTeam
Author-email: andrewsmedina@gmail.com
License: BSD
Project-URL: Documentation, https://splinter.readthedocs.io/
Project-URL: Changelog, https://github.com/cobrateam/splinter/tree/master/docs/news
Project-URL: Source, https://github.com/cobrateam/splinter/
Project-URL: Tracker, https://github.com/cobrateam/splinter/issues
Classifier: License :: OSI Approved :: BSD License
Classifier: Programming Language :: Python :: 3
Classifier: Programming Language :: Python :: 3.8
Classifier: Programming Language :: Python :: 3.9
Classifier: Programming Language :: Python :: 3.10
Classifier: Programming Language :: Python :: 3.11
Classifier: Programming Language :: Python :: 3.12
License-File: LICENSE
License-File: AUTHORS
Requires-Dist: urllib3<3.0,>=1.26.14
Provides-Extra: zope-testbrowser
Requires-Dist: zope.testbrowser>=6.0; extra == "zope-testbrowser"
Requires-Dist: lxml>=4.2.4; extra == "zope-testbrowser"
Requires-Dist: cssselect; extra == "zope-testbrowser"
Provides-Extra: django
Requires-Dist: Django>=2.0.6; extra == "django"
Requires-Dist: lxml>=4.2.4; extra == "django"
Requires-Dist: cssselect; extra == "django"
Provides-Extra: flask
Requires-Dist: Flask>=2.3.2; extra == "flask"
Requires-Dist: lxml>=4.2.4; extra == "flask"
Requires-Dist: cssselect; extra == "flask"
Provides-Extra: selenium
Requires-Dist: selenium<4.17.0,>=4.1.0; extra == "selenium"
